quantum_101/__init__.py
quantum_101/konfig_elektron.py
quantum_101/kuantum_azimut.py
quantum_101/kuantum_magnetik.py
quantum_101/kuantum_spin.py
quantum_101/kuantum_utama.py
quantum_101/nomor_atom.py
quantum_101-0.3.dist-info/METADATA
quantum_101-0.3.dist-info/WHEEL
quantum_101-0.3.dist-info/top_level.txt
quantum_101-0.3.dist-info/RECORD
