Metadata-Version: 2.1
Name: quantum_101
Version: 0.3
Summary: package tentang operasi bilangan kuantum
Author: MegIv
